ghoul/__init__.py
ghoul/ghoul.py
ghoul/main.py
ghoul-0.1.0.dist-info/DESCRIPTION.rst
ghoul-0.1.0.dist-info/METADATA
ghoul-0.1.0.dist-info/RECORD
ghoul-0.1.0.dist-info/WHEEL
ghoul-0.1.0.dist-info/metadata.json
ghoul-0.1.0.dist-info/top_level.txt
