Metadata-Version: 2.0
Name: ghoul
Version: 0.1.0
Summary: Bottom-up procedural generation
Home-page: https://github.com/scrudgey/ghoul
Author: Ryan Foltz
Author-email: scrudgey@gmail.com
License: MIT license
Keywords: ghoul
Platform: UNKNOWN
Classifier: Development Status :: 2 - Pre-Alpha
Classifier: Intended Audience :: Developers
Classifier: License :: OSI Approved :: MIT License
Classifier: Natural Language :: English
Classifier: Programming Language :: Python :: 2
Classifier: Programming Language :: Python :: 2.7
Classifier: Programming Language :: Python :: 3
Classifier: Programming Language :: Python :: 3.4
Classifier: Programming Language :: Python :: 3.5
Classifier: Programming Language :: Python :: 3.6
Classifier: Programming Language :: Python :: 3.7
